tic_tac_toe_backends/__init__.py
tic_tac_toe_backends/sdk.py
tic_tac_toe_backends/sdkconfiguration.py
tic_tac_toe_backends/_hooks/__init__.py
tic_tac_toe_backends/_hooks/sdkhooks.py
tic_tac_toe_backends/_hooks/types.py
tic_tac_toe_backends/models/__init__.py
tic_tac_toe_backends/models/errors/__init__.py
tic_tac_toe_backends/models/errors/sdkerror.py
tic_tac_toe_backends/models/operations/__init__.py
tic_tac_toe_backends/models/operations/get_.py
tic_tac_toe_backends/models/operations/get_version.py
tic_tac_toe_backends/models/operations/put_games.py
tic_tac_toe_backends/models/shared/__init__.py
tic_tac_toe_backends/models/shared/move.py
tic_tac_toe_backends/models/shared/moveparameter.py
tic_tac_toe_backends/models/shared/version.py
tic_tac_toe_backends/utils/__init__.py
tic_tac_toe_backends/utils/retries.py
tic_tac_toe_backends/utils/utils.py
tic_tac_toe_backend-5.2.1.dist-info/LICENSE.md
tic_tac_toe_backend-5.2.1.dist-info/METADATA
tic_tac_toe_backend-5.2.1.dist-info/WHEEL
tic_tac_toe_backend-5.2.1.dist-info/top_level.txt
tic_tac_toe_backend-5.2.1.dist-info/RECORD
